gshoppy/__init__.py
gshoppy/constants.py
gshoppy/utils.py
gshoppy/services/__init__.py
gshoppy/services/core.py
gshoppy/services/models.py
gshoppy/services/product.py
shoppy/__init__.py
src/__init__.py
src/constants.py
src/utils.py
src/services/__init__.py
src/services/core.py
src/services/models.py
src/services/product.py
gshoppy-0.0.15.dist-info/LICENCE
gshoppy-0.0.15.dist-info/METADATA
gshoppy-0.0.15.dist-info/WHEEL
gshoppy-0.0.15.dist-info/top_level.txt
gshoppy-0.0.15.dist-info/RECORD
